llm_openrouter.py
llm_openrouter-0.5.dist-info/licenses/LICENSE
llm_openrouter-0.5.dist-info/METADATA
llm_openrouter-0.5.dist-info/WHEEL
llm_openrouter-0.5.dist-info/entry_points.txt
llm_openrouter-0.5.dist-info/top_level.txt
llm_openrouter-0.5.dist-info/RECORD
