Metadata-Version: 2.4
Name: llm-openrouter
Version: 0.5
Summary: LLM plugin for models hosted by OpenRouter
Author: Simon Willison
License: Apache-2.0
Project-URL: Homepage, https://github.com/simonw/llm-openrouter
Project-URL: Changelog, https://github.com/simonw/llm-openrouter/releases
Project-URL: Issues, https://github.com/simonw/llm-openrouter/issues
Project-URL: CI, https://github.com/simonw/llm-openrouter/actions
Classifier: License :: OSI Approved :: Apache Software License
License-File: LICENSE
Requires-Dist: llm>=0.27.1
Requires-Dist: httpx
Requires-Dist: openai>=1.57.0
Provides-Extra: test
Requires-Dist: pytest; extra == "test"
Requires-Dist: pytest-recording; extra == "test"
Requires-Dist: inline-snapshot; extra == "test"
Dynamic: license-file
